<?xml version="1.0" encoding="UTF-8"?>
<!DOCTYPE tiles-definitions PUBLIC "-//Apache Software Foundation//DTD Tiles Configuration 2.1//EN" "http://tiles.apache.org/dtds/tiles-config_2_1.dtd">

<tiles-definitions>
	<definition name="grouponTemplate" template="/WEB-INF/views/template/layout.jsp">
		<put-attribute name="htmlHead" value="/WEB-INF/views/common/header.jsp" />
		<put-attribute name="nav"
			value="/WEB-INF/views/common/navigation.jsp" />
		<!-- <put-attribute name="innerNav" value="/WEB-INF/views/common/innerNavigation.jsp" 
			/> -->
		<put-attribute name="footer" value="/WEB-INF/views/common/footer.jsp" />
	</definition>

	<definition name="home.view" extends="grouponTemplate">
		<put-attribute name="title" cascade="true"
			value="Purposeful Communities" />
		<put-attribute name="body" value="/WEB-INF/views/home.jsp" />
		<put-list-attribute name="cssFiles" cascade="true">
			<add-attribute value="/home.css" />
		</put-list-attribute>
		<put-list-attribute name="jsFiles" cascade="true">
			<add-attribute value="/home.js" />
		</put-list-attribute>
	</definition>

	<definition name="homeguest.view" extends="grouponTemplate">
		<put-attribute name="title" cascade="true"
			value="Purposeful Communities" />
		<put-attribute name="body" value="/WEB-INF/views/homeguest.jsp" />
		<put-list-attribute name="cssFiles" cascade="true">
			<add-attribute value="/home.css" />
		</put-list-attribute>
		<put-list-attribute name="jsFiles" cascade="true">
			<add-attribute value="/home.js" />
		</put-list-attribute>
	</definition>

	<definition name="createCommunity.view" extends="grouponTemplate">
		<put-attribute name="title" cascade="true" value="Create a Community" />
		<put-attribute name="body" value="/WEB-INF/views/createCommunity.jsp" />
		<put-list-attribute name="cssFiles" cascade="true">
			<add-attribute value="/jquery-ui.css" />
			<add-attribute value="/select2.css" />
		</put-list-attribute>
		<put-list-attribute name="jsFiles" cascade="true">
			<add-attribute value="/jquery-ui.js" />
			<add-attribute value="/select2.js" />
			<add-attribute value="/createCommunity.js" />
		</put-list-attribute>
	</definition>

	<definition name="community.view" extends="grouponTemplate">
		<put-attribute name="title" cascade="true" value="View Community" />
		<put-attribute name="body" value="/WEB-INF/views/community.jsp" />
		<put-list-attribute name="jsFiles" cascade="true">
			<add-attribute value="/community.js" />
		</put-list-attribute>
	</definition>

	<definition name="signup.view" extends="grouponTemplate">
		<put-attribute name="title" cascade="true"
			value="Signup for Task Together!" />
		<put-attribute name="body" value="/WEB-INF/views/signup.jsp" />
	</definition>

	<definition name="userDeactivated.view" extends="grouponTemplate">
		<put-attribute name="title" cascade="true"
			value="Activate Your Account!" />
		<put-attribute name="body" value="/WEB-INF/views/userDeactivated.jsp" />
	</definition>

	<definition name="userBanned.view" extends="grouponTemplate">
		<put-attribute name="title" cascade="true"
			value="Banned! Contact Us!" />
		<put-attribute name="body" value="/WEB-INF/views/userBanned.jsp" />
	</definition>

	<definition name="userDeleted.view" extends="grouponTemplate">
		<put-attribute name="title" cascade="true"
			value="Deleted! Contact Us!" />
		<put-attribute name="body" value="/WEB-INF/views/userDeleted.jsp" />
	</definition>

	<definition name="createTask.view" extends="grouponTemplate">
		<put-attribute name="title" cascade="true" value="Create a Task" />
		<put-attribute name="body" value="/WEB-INF/views/createTask.jsp" />
		<put-list-attribute name="cssFiles" cascade="true">
			<add-attribute value="/jquery-ui.css" />
			<add-attribute value="/select2.css" />
		</put-list-attribute>
		<put-list-attribute name="jsFiles" cascade="true">
			<add-attribute value="/jquery-ui.js" />
			<add-attribute value="/select2.js" />
			<add-attribute value="/createTask.js" />
		</put-list-attribute>
	</definition>
	
	<definition name="advancedSearch.view" extends="grouponTemplate">
		<put-attribute name="title" cascade="true"
			value="Search" />
		<put-attribute name="body" value="/WEB-INF/views/advancedSearch.jsp" />
	</definition>
	
	<definition name="task.view" extends="grouponTemplate">
		<put-attribute name="title" cascade="true" value="Task" />
		<put-attribute name="body" value="/WEB-INF/views/task.jsp" />
		<put-list-attribute name="cssFiles" cascade="true">
			<add-attribute value="/jquery-ui.css" />
			<add-attribute value="/select2.css" />
		</put-list-attribute>
		<put-list-attribute name="jsFiles" cascade="true">
			<add-attribute value="/jquery-ui.js" />
			<add-attribute value="/select2.js" />
			<add-attribute value="/task.js" />
		</put-list-attribute>
	</definition>

	<definition name="profile.view" extends="grouponTemplate">
		<put-attribute name="title" cascade="true" value="Profile" />
		<put-attribute name="body" value="/WEB-INF/views/profile.jsp" />
		<put-list-attribute name="cssFiles" cascade="true">
		</put-list-attribute>
		<put-list-attribute name="jsFiles" cascade="true">
		</put-list-attribute>
	</definition>
	
	<definition name="createTaskType.view" extends="grouponTemplate">
		<put-attribute name="title" cascade="true" value="Create Task Type" />
		<put-attribute name="body" value="/WEB-INF/views/createTaskType.jsp" />
		<put-list-attribute name="cssFiles" cascade="true">
		</put-list-attribute>
		<put-list-attribute name="jsFiles" cascade="true">
		    <add-attribute value="/createTaskType.js" />
		</put-list-attribute>
	</definition>
</tiles-definitions>